codex_apply_patch-0.4.0.dist-info/METADATA
codex_apply_patch-0.4.0.dist-info/WHEEL
codex_apply_patch-0.4.0.dist-info/licenses/LICENSE
codex_apply_patch/.gitignore
codex_apply_patch/__init__.py
codex_apply_patch/codex_apply_patch.cp313-win32.pyd
codex_apply_patch-0.4.0.dist-info/RECORD
