Metadata-Version: 2.4
Name: codex-apply-patch
Version: 0.4.0
Classifier: Development Status :: 4 - Beta
Classifier: Intended Audience :: Developers
Classifier: License :: OSI Approved :: Apache Software License
Classifier: Operating System :: OS Independent
Classifier: Programming Language :: Python :: 3
Classifier: Programming Language :: Python :: 3.8
Classifier: Programming Language :: Python :: 3.9
Classifier: Programming Language :: Python :: 3.10
Classifier: Programming Language :: Python :: 3.11
Classifier: Programming Language :: Python :: 3.12
Classifier: Programming Language :: Rust
Classifier: Topic :: Software Development :: Libraries :: Python Modules
Classifier: Topic :: Text Processing
Classifier: Topic :: Utilities
License-File: LICENSE
Summary: A CLI tool and Python library for applying patches using a custom patch format designed for AI coding assistants
Keywords: patch,apply,cli,diff,ai
Author: OpenAI <support@openai.com>
Author-email: OpenAI <support@openai.com>
License: Apache-2.0
Requires-Python: >=3.8
Project-URL: Homepage, https://github.com/openai/codex-apply-patch
Project-URL: Repository, https://github.com/openai/codex-apply-patch
Project-URL: Documentation, https://github.com/openai/codex-apply-patch
Project-URL: Bug Reports, https://github.com/openai/codex-apply-patch/issues
Project-URL: Source, https://github.com/openai/codex-apply-patch
